hateno/__init__.py
hateno/checkers.py
hateno/errors.py
hateno/events.py
hateno/explorer.py
hateno/fcollection.py
hateno/fixers.py
hateno/folder.py
hateno/generator.py
hateno/generators.py
hateno/jobs.py
hateno/jsonfiles.py
hateno/maker.py
hateno/manager.py
hateno/mapper.py
hateno/namers.py
hateno/remote.py
hateno/simulation.py
hateno/string.py
hateno/ui.py
hateno/utils.py
hateno/explorer/__init__.py
hateno/explorer/errors.py
hateno/explorer/explorer.py
hateno/explorer/mapper.py
hateno/explorer/ui.py
hateno/folder/__init__.py
hateno/folder/checkers.py
hateno/folder/errors.py
hateno/folder/fixers.py
hateno/folder/folder.py
hateno/folder/namers.py
hateno/generator/__init__.py
hateno/generator/errors.py
hateno/generator/generator.py
hateno/job/__init__.py
hateno/job/client.py
hateno/job/errors.py
hateno/job/filewatcher.py
hateno/job/job.py
hateno/job/server.py
hateno/maker/__init__.py
hateno/maker/errors.py
hateno/maker/maker.py
hateno/maker/ui.py
hateno/manager/__init__.py
hateno/manager/errors.py
hateno/manager/manager.py
hateno/remote/__init__.py
hateno/remote/errors.py
hateno/remote/folder.py
hateno/remote/localsftp.py
hateno/remote/sftp.py
hateno/simulation/__init__.py
hateno/simulation/basesetting.py
hateno/simulation/errors.py
hateno/simulation/globalsetting.py
hateno/simulation/setting.py
hateno/simulation/simulation.py
hateno/ui/__init__.py
hateno/ui/errors.py
hateno/ui/item.py
hateno/ui/progressbar.py
hateno/ui/textline.py
hateno/ui/ui.py
hateno/utils/__init__.py
hateno/utils/errors.py
hateno/utils/events.py
hateno/utils/fcollection.py
hateno/utils/jsonfiles.py
hateno/utils/lockedfile.py
hateno/utils/string.py
hateno/utils/utils.py
hateno-0.16.data/scripts/hateno
hateno-0.16.data/scripts/hateno-clear
hateno-0.16.data/scripts/hateno-exec
hateno-0.16.data/scripts/hateno-explorer
hateno-0.16.data/scripts/hateno-generator
hateno-0.16.data/scripts/hateno-get-settings
hateno-0.16.data/scripts/hateno-init
hateno-0.16.data/scripts/hateno-job
hateno-0.16.dist-info/LICENSE
hateno-0.16.dist-info/METADATA
hateno-0.16.dist-info/WHEEL
hateno-0.16.dist-info/top_level.txt
hateno-0.16.dist-info/RECORD
