Metadata-Version: 2.1
Name: hateno
Version: 0.16
Summary: Hateno is a simulations manager, aimed to automate the process of managing and generating a high number of simulations.
Home-page: https://github.com/JeremyHeleine/Hateno
Author: Jérémy Heleine
Author-email: jeremy.heleine@gmail.com
License: MIT License
Keywords: simulations,automation
Platform: UNKNOWN
Classifier: Programming Language :: Python :: 3
Classifier: License :: OSI Approved :: MIT License
Classifier: Operating System :: OS Independent
Requires-Python: >=3.7
Requires-Dist: paramiko
Requires-Dist: tabulate
